{"commitInfo":{"timestamp":1759532194300,"operation":"ADD COLUMNS","operationParameters":{"columns":"[{\"column\":{\"name\":\"fraud_reported_bool\",\"type\":\"boolean\",\"nullable\":true,\"metadata\":{}}}]"},"readVersion":9,"isolationLevel":"Serializable","isBlindAppend":true,"operationMetrics":{},"engineInfo":"Apache-Spark/3.4.1 Delta-Lake/2.4.0","txnId":"4a34e100-b41b-44f0-b667-b7b4b1e5e852"}}
{"metaData":{"id":"0788ecee-0333-4dd4-b619-5eb8be941df1","format":{"provider":"parquet","options":{}},"schemaString":"{\"type\":\"struct\",\"fields\":[{\"name\":\"months_as_customer\",\"type\":\"string\",\"nullable\":true,\"metadata\":{}},{\"name\":\"age\",\"type\":\"string\",\"nullable\":true,\"metadata\":{}},{\"name\":\"policy_number\",\"type\":\"string\",\"nullable\":true,\"metadata\":{}},{\"name\":\"policy_bind_date\",\"type\":\"string\",\"nullable\":true,\"metadata\":{}},{\"name\":\"policy_state\",\"type\":\"string\",\"nullable\":true,\"metadata\":{}},{\"name\":\"policy_csl\",\"type\":\"string\",\"nullable\":true,\"metadata\":{}},{\"name\":\"policy_deductable\",\"type\":\"string\",\"nullable\":true,\"metadata\":{}},{\"name\":\"policy_annual_premium\",\"type\":\"string\",\"nullable\":true,\"metadata\":{}},{\"name\":\"umbrella_limit\",\"type\":\"string\",\"nullable\":true,\"metadata\":{}},{\"name\":\"insured_zip\",\"type\":\"string\",\"nullable\":true,\"metadata\":{}},{\"name\":\"insured_sex\",\"type\":\"string\",\"nullable\":true,\"metadata\":{}},{\"name\":\"insured_education_level\",\"type\":\"string\",\"nullable\":true,\"metadata\":{}},{\"name\":\"insured_occupation\",\"type\":\"string\",\"nullable\":true,\"metadata\":{}},{\"name\":\"insured_hobbies\",\"type\":\"string\",\"nullable\":true,\"metadata\":{}},{\"name\":\"insured_relationship\",\"type\":\"string\",\"nullable\":true,\"metadata\":{}},{\"name\":\"capital_gains\",\"type\":\"string\",\"nullable\":true,\"metadata\":{}},{\"name\":\"capital_loss\",\"type\":\"string\",\"nullable\":true,\"metadata\":{}},{\"name\":\"incident_date\",\"type\":\"string\",\"nullable\":true,\"metadata\":{}},{\"name\":\"incident_type\",\"type\":\"string\",\"nullable\":true,\"metadata\":{}},{\"name\":\"collision_type\",\"type\":\"string\",\"nullable\":true,\"metadata\":{}},{\"name\":\"incident_severity\",\"type\":\"string\",\"nullable\":true,\"metadata\":{}},{\"name\":\"authorities_contacted\",\"type\":\"string\",\"nullable\":true,\"metadata\":{}},{\"name\":\"incident_state\",\"type\":\"string\",\"nullable\":true,\"metadata\":{}},{\"name\":\"incident_city\",\"type\":\"string\",\"nullable\":true,\"metadata\":{}},{\"name\":\"incident_location\",\"type\":\"string\",\"nullable\":true,\"metadata\":{}},{\"name\":\"incident_hour_of_the_day\",\"type\":\"string\",\"nullable\":true,\"metadata\":{}},{\"name\":\"number_of_vehicles_involved\",\"type\":\"string\",\"nullable\":true,\"metadata\":{}},{\"name\":\"property_damage\",\"type\":\"string\",\"nullable\":true,\"metadata\":{}},{\"name\":\"bodily_injuries\",\"type\":\"string\",\"nullable\":true,\"metadata\":{}},{\"name\":\"witnesses\",\"type\":\"string\",\"nullable\":true,\"metadata\":{}},{\"name\":\"police_report_available\",\"type\":\"string\",\"nullable\":true,\"metadata\":{}},{\"name\":\"total_claim_amount\",\"type\":\"string\",\"nullable\":true,\"metadata\":{}},{\"name\":\"injury_claim\",\"type\":\"string\",\"nullable\":true,\"metadata\":{}},{\"name\":\"property_claim\",\"type\":\"string\",\"nullable\":true,\"metadata\":{}},{\"name\":\"vehicle_claim\",\"type\":\"string\",\"nullable\":true,\"metadata\":{}},{\"name\":\"auto_make\",\"type\":\"string\",\"nullable\":true,\"metadata\":{}},{\"name\":\"auto_model\",\"type\":\"string\",\"nullable\":true,\"metadata\":{}},{\"name\":\"auto_year\",\"type\":\"string\",\"nullable\":true,\"metadata\":{}},{\"name\":\"fraud_reported\",\"type\":\"string\",\"nullable\":true,\"metadata\":{}},{\"name\":\"_c39\",\"type\":\"string\",\"nullable\":true,\"metadata\":{}},{\"name\":\"missing_data\",\"type\":\"boolean\",\"nullable\":true,\"metadata\":{}},{\"name\":\"age_group\",\"type\":\"string\",\"nullable\":true,\"metadata\":{}},{\"name\":\"age_risk_score\",\"type\":\"float\",\"nullable\":true,\"metadata\":{}},{\"name\":\"risque_selon_lanciennete\",\"type\":\"float\",\"nullable\":true,\"metadata\":{}},{\"name\":\"risque_selon_la_fraude\",\"type\":\"float\",\"nullable\":true,\"metadata\":{}},{\"name\":\"risque_total\",\"type\":\"float\",\"nullable\":true,\"metadata\":{}},{\"name\":\"cathegorie_risque\",\"type\":\"string\",\"nullable\":true,\"metadata\":{}},{\"name\":\"fraud_reported_bool\",\"type\":\"boolean\",\"nullable\":true,\"metadata\":{}}]}","partitionColumns":[],"configuration":{},"createdTime":1759532177288}}
